[
    "各企画",
    [
        "1年生",
        {
            "groupName":"1-1",
            "projectName":"たこやき",
            "description":"出来立てのたこやきはいかが？"
        },
        {
            "groupName":"1-2",
            "projectName":"たこやき",
            "description":"出来立てのたこやきはいかが？"
        },
        {
            "groupName":"1-3",
            "projectName":"たこやき",
            "description":"出来立てのたこやきはいかが？"
        },
        {
            "groupName":"1-4",
            "projectName":"たこやき",
            "description":"出来立てのたこやきはいかが？"
        },
        {
            "groupName":"1-5",
            "projectName":"たこやき",
            "description":"出来立てのたこやきはいかが？"
        }
    ],
    [
        "2年生",
        {
            "groupName":"2-1",
            "projectName":"たこやき",
            "description":"出来立てのたこやきはいかが？"
        },
        {
            "groupName":"2-2",
            "projectName":"たこやき",
            "description":"出来立てのたこやきはいかが？"
        },
        {
            "groupName":"2-3",
            "projectName":"たこやき",
            "description":"出来立てのたこやきはいかが？"
        },
        {
            "groupName":"2-4",
            "projectName":"たこやき",
            "description":"出来立てのたこやきはいかが？"
        },
        {
            "groupName":"2-5",
            "projectName":"たこやき",
            "description":"出来立てのたこやきはいかが？"
        }
    ],
    [
        "3年生"
    ],
    [
        "4年生"
    ],
    [
        "5年生"
    ],
    [
        "運動部①"
    ],
    [
        "運動部②"
    ],
    [
        "文化部"
    ],
    [
        "愛好会"
    ],
    [
        "有志"
    ]
]